parent_import/__init__.py
parent_import-0.0.1.dist-info/LICENSE
parent_import-0.0.1.dist-info/METADATA
parent_import-0.0.1.dist-info/WHEEL
parent_import-0.0.1.dist-info/top_level.txt
parent_import-0.0.1.dist-info/RECORD
