Metadata-Version: 2.1
Name: parent-import
Version: 0.0.1
Summary: This package makes it easier to import from parent directory.
Home-page: https://github.com/simitii/python_parent_import
Author: Samet Demir
Author-email: demir.samet@hotmail.com
License: UNKNOWN
Platform: UNKNOWN
Classifier: Programming Language :: Python :: 3
Classifier: License :: OSI Approved :: MIT License
Classifier: Operating System :: OS Independent
Requires-Python: >=3.5
